vpd/__init__.py
vpd/arguments.py
vpd/cid.py
vpd/cmp.py
vpd/iterable.py
vpd/yaml_dict.py
vpd/legacy/__init__.py
vpd/legacy/arguments.py
vpd/legacy/cid.py
vpd/legacy/cmp.py
vpd/legacy/iterable.py
vpd/legacy/yaml_dict.py
vpd/next/__init__.py
vpd/next/util.py
vpd/next/graph/__init__.py
vpd/next/graph/api.py
vpd/next/graph/complex_queries.py
vpd/next/graph/functions.py
vpd/next/graph/input_object.py
vpd/next/graph/min_export.py
vpd/next/graph/model.py
vpd/next/graph/plugin_system.py
vpd/next/k8s/__init__.py
vpd/next/k8s/config.py
vpd/simple/__init__.py
vpd-0.9.12.dist-info/LICENSE
vpd-0.9.12.dist-info/METADATA
vpd-0.9.12.dist-info/WHEEL
vpd-0.9.12.dist-info/top_level.txt
vpd-0.9.12.dist-info/RECORD
