Metadata-Version: 2.1
Name: vpd
Version: 0.9.12
Summary: VirtualPathDictChains. Hierarchical, Addressable Dicts, potentially using YaML
Home-page: https://github.com/dbotwinick/python-vpd
Author: Drew Botwinick
Author-email: foss@drewbotwinick.com
License: UNKNOWN
Platform: UNKNOWN
Classifier: Development Status :: 4 - Beta
Classifier: Intended Audience :: Developers
Classifier: Programming Language :: Python :: 3
Classifier: License :: OSI Approved :: BSD License
Classifier: Operating System :: OS Independent
Requires-Python: >=3.9
License-File: LICENSE
Requires-Dist: six
Requires-Dist: PyYAML
